<?xml version="1.0" encoding="UTF-8" standalone="yes"?>
<template encoding-version="1.2">
    <description>Full pipeline: 
- read records from database 
- send the binary documents to tika 
- convert JSON result to AVRO
- store the result in ES and DB</description>
    <groupId>d8c803bb-016d-1000-434b-06893806e64d</groupId>
    <name>Docs-DB-Tika-AVRO-ES+DB</name>
    <snippet>
        <connections>
            <id>05fd25e7-a924-3b6e-0000-000000000000</id>
            <parentGroupId>c1783d42-645f-3380-0000-000000000000</parentGroupId>
            <backPressureDataSizeThreshold>100 MB</backPressureDataSizeThreshold>
            <backPressureObjectThreshold>10000</backPressureObjectThreshold>
            <destination>
                <groupId>c1783d42-645f-3380-0000-000000000000</groupId>
                <id>407c5cd1-0a0c-3634-0000-000000000000</id>
                <type>FUNNEL</type>
            </destination>
            <flowFileExpiration>0 sec</flowFileExpiration>
            <labelIndex>1</labelIndex>
            <loadBalanceCompression>DO_NOT_COMPRESS</loadBalanceCompression>
            <loadBalancePartitionAttribute></loadBalancePartitionAttribute>
            <loadBalanceStatus>LOAD_BALANCE_NOT_CONFIGURED</loadBalanceStatus>
            <loadBalanceStrategy>DO_NOT_LOAD_BALANCE</loadBalanceStrategy>
            <name></name>
            <selectedRelationships>failure</selectedRelationships>
            <source>
                <groupId>c1783d42-645f-3380-0000-000000000000</groupId>
                <id>9ca0eb06-eb43-3e1a-0000-000000000000</id>
                <type>PROCESSOR</type>
            </source>
            <zIndex>0</zIndex>
        </connections>
        <connections>
            <id>400549ac-d0db-3993-0000-000000000000</id>
            <parentGroupId>c1783d42-645f-3380-0000-000000000000</parentGroupId>
            <backPressureDataSizeThreshold>100 MB</backPressureDataSizeThreshold>
            <backPressureObjectThreshold>10000</backPressureObjectThreshold>
            <destination>
                <groupId>c1783d42-645f-3380-0000-000000000000</groupId>
                <id>9ca0eb06-eb43-3e1a-0000-000000000000</id>
                <type>PROCESSOR</type>
            </destination>
            <flowFileExpiration>0 sec</flowFileExpiration>
            <labelIndex>1</labelIndex>
            <loadBalanceCompression>DO_NOT_COMPRESS</loadBalanceCompression>
            <loadBalancePartitionAttribute></loadBalancePartitionAttribute>
            <loadBalanceStatus>LOAD_BALANCE_NOT_CONFIGURED</loadBalanceStatus>
            <loadBalanceStrategy>DO_NOT_LOAD_BALANCE</loadBalanceStrategy>
            <name></name>
            <selectedRelationships>success</selectedRelationships>
            <source>
                <groupId>c1783d42-645f-3380-0000-000000000000</groupId>
                <id>614be727-96a2-32b4-0000-000000000000</id>
                <type>PROCESSOR</type>
            </source>
            <zIndex>0</zIndex>
        </connections>
        <connections>
            <id>54cf06ad-dda1-3f78-0000-000000000000</id>
            <parentGroupId>c1783d42-645f-3380-0000-000000000000</parentGroupId>
            <backPressureDataSizeThreshold>100 MB</backPressureDataSizeThreshold>
            <backPressureObjectThreshold>10000</backPressureObjectThreshold>
            <destination>
                <groupId>c1783d42-645f-3380-0000-000000000000</groupId>
                <id>e31e1369-1655-37e8-0000-000000000000</id>
                <type>PROCESSOR</type>
            </destination>
            <flowFileExpiration>0 sec</flowFileExpiration>
            <labelIndex>1</labelIndex>
            <loadBalanceCompression>DO_NOT_COMPRESS</loadBalanceCompression>
            <loadBalancePartitionAttribute></loadBalancePartitionAttribute>
            <loadBalanceStatus>LOAD_BALANCE_NOT_CONFIGURED</loadBalanceStatus>
            <loadBalanceStrategy>DO_NOT_LOAD_BALANCE</loadBalanceStrategy>
            <name></name>
            <selectedRelationships>success</selectedRelationships>
            <source>
                <groupId>c1783d42-645f-3380-0000-000000000000</groupId>
                <id>614be727-96a2-32b4-0000-000000000000</id>
                <type>PROCESSOR</type>
            </source>
            <zIndex>0</zIndex>
        </connections>
        <connections>
            <id>5e60a94a-e2fe-3aa0-0000-000000000000</id>
            <parentGroupId>c1783d42-645f-3380-0000-000000000000</parentGroupId>
            <backPressureDataSizeThreshold>1 GB</backPressureDataSizeThreshold>
            <backPressureObjectThreshold>10000</backPressureObjectThreshold>
            <destination>
                <groupId>c1783d42-645f-3380-0000-000000000000</groupId>
                <id>5ce096b6-e3f8-32f0-0000-000000000000</id>
                <type>FUNNEL</type>
            </destination>
            <flowFileExpiration>0 sec</flowFileExpiration>
            <labelIndex>1</labelIndex>
            <loadBalanceCompression>DO_NOT_COMPRESS</loadBalanceCompression>
            <loadBalancePartitionAttribute></loadBalancePartitionAttribute>
            <loadBalanceStatus>LOAD_BALANCE_NOT_CONFIGURED</loadBalanceStatus>
            <loadBalanceStrategy>DO_NOT_LOAD_BALANCE</loadBalanceStrategy>
            <name></name>
            <selectedRelationships>failure</selectedRelationships>
            <source>
                <groupId>c1783d42-645f-3380-0000-000000000000</groupId>
                <id>005c59d5-16b8-375e-0000-000000000000</id>
                <type>PROCESSOR</type>
            </source>
            <zIndex>0</zIndex>
        </connections>
        <connections>
            <id>5f5dd8c9-c13b-3e8d-0000-000000000000</id>
            <parentGroupId>c1783d42-645f-3380-0000-000000000000</parentGroupId>
            <backPressureDataSizeThreshold>1 GB</backPressureDataSizeThreshold>
            <backPressureObjectThreshold>10000</backPressureObjectThreshold>
            <destination>
                <groupId>c1783d42-645f-3380-0000-000000000000</groupId>
                <id>4d1a2e16-aa25-38ed-0000-000000000000</id>
                <type>PROCESSOR</type>
            </destination>
            <flowFileExpiration>0 sec</flowFileExpiration>
            <labelIndex>1</labelIndex>
            <loadBalanceCompression>DO_NOT_COMPRESS</loadBalanceCompression>
            <loadBalancePartitionAttribute></loadBalancePartitionAttribute>
            <loadBalanceStatus>LOAD_BALANCE_NOT_CONFIGURED</loadBalanceStatus>
            <loadBalanceStrategy>DO_NOT_LOAD_BALANCE</loadBalanceStrategy>
            <name></name>
            <selectedRelationships>success</selectedRelationships>
            <source>
                <groupId>c1783d42-645f-3380-0000-000000000000</groupId>
                <id>f6dfc4f4-2311-371b-0000-000000000000</id>
                <type>PROCESSOR</type>
            </source>
            <zIndex>0</zIndex>
        </connections>
        <connections>
            <id>61762fe7-e01a-383f-0000-000000000000</id>
            <parentGroupId>c1783d42-645f-3380-0000-000000000000</parentGroupId>
            <backPressureDataSizeThreshold>1 GB</backPressureDataSizeThreshold>
            <backPressureObjectThreshold>10000</backPressureObjectThreshold>
            <destination>
                <groupId>c1783d42-645f-3380-0000-000000000000</groupId>
                <id>005c59d5-16b8-375e-0000-000000000000</id>
                <type>PROCESSOR</type>
            </destination>
            <flowFileExpiration>0 sec</flowFileExpiration>
            <labelIndex>1</labelIndex>
            <loadBalanceCompression>DO_NOT_COMPRESS</loadBalanceCompression>
            <loadBalancePartitionAttribute></loadBalancePartitionAttribute>
            <loadBalanceStatus>LOAD_BALANCE_NOT_CONFIGURED</loadBalanceStatus>
            <loadBalanceStrategy>DO_NOT_LOAD_BALANCE</loadBalanceStrategy>
            <name></name>
            <selectedRelationships>Response</selectedRelationships>
            <source>
                <groupId>c1783d42-645f-3380-0000-000000000000</groupId>
                <id>89eef85f-3cfa-303b-0000-000000000000</id>
                <type>PROCESSOR</type>
            </source>
            <zIndex>0</zIndex>
        </connections>
        <connections>
            <id>79df36fd-5070-3c73-0000-000000000000</id>
            <parentGroupId>c1783d42-645f-3380-0000-000000000000</parentGroupId>
            <backPressureDataSizeThreshold>1 GB</backPressureDataSizeThreshold>
            <backPressureObjectThreshold>10000</backPressureObjectThreshold>
            <destination>
                <groupId>c1783d42-645f-3380-0000-000000000000</groupId>
                <id>fa42dc0a-369e-348c-0000-000000000000</id>
                <type>FUNNEL</type>
            </destination>
            <flowFileExpiration>0 sec</flowFileExpiration>
            <labelIndex>1</labelIndex>
            <loadBalanceCompression>DO_NOT_COMPRESS</loadBalanceCompression>
            <loadBalancePartitionAttribute></loadBalancePartitionAttribute>
            <loadBalanceStatus>LOAD_BALANCE_NOT_CONFIGURED</loadBalanceStatus>
            <loadBalanceStrategy>DO_NOT_LOAD_BALANCE</loadBalanceStrategy>
            <name></name>
            <selectedRelationships>Failure</selectedRelationships>
            <selectedRelationships>No Retry</selectedRelationships>
            <source>
                <groupId>c1783d42-645f-3380-0000-000000000000</groupId>
                <id>89eef85f-3cfa-303b-0000-000000000000</id>
                <type>PROCESSOR</type>
            </source>
            <zIndex>0</zIndex>
        </connections>
        <connections>
            <id>86b56d66-bacf-3c8c-0000-000000000000</id>
            <parentGroupId>c1783d42-645f-3380-0000-000000000000</parentGroupId>
            <backPressureDataSizeThreshold>1 GB</backPressureDataSizeThreshold>
            <backPressureObjectThreshold>10000</backPressureObjectThreshold>
            <destination>
                <groupId>c1783d42-645f-3380-0000-000000000000</groupId>
                <id>89eef85f-3cfa-303b-0000-000000000000</id>
                <type>PROCESSOR</type>
            </destination>
            <flowFileExpiration>0 sec</flowFileExpiration>
            <labelIndex>1</labelIndex>
            <loadBalanceCompression>DO_NOT_COMPRESS</loadBalanceCompression>
            <loadBalancePartitionAttribute></loadBalancePartitionAttribute>
            <loadBalanceStatus>LOAD_BALANCE_NOT_CONFIGURED</loadBalanceStatus>
            <loadBalanceStrategy>DO_NOT_LOAD_BALANCE</loadBalanceStrategy>
            <name></name>
            <selectedRelationships>success</selectedRelationships>
            <source>
                <groupId>c1783d42-645f-3380-0000-000000000000</groupId>
                <id>4d1a2e16-aa25-38ed-0000-000000000000</id>
                <type>PROCESSOR</type>
            </source>
            <zIndex>0</zIndex>
        </connections>
        <connections>
            <id>9e2d6c23-fafd-3e53-0000-000000000000</id>
            <parentGroupId>c1783d42-645f-3380-0000-000000000000</parentGroupId>
            <backPressureDataSizeThreshold>100 MB</backPressureDataSizeThreshold>
            <backPressureObjectThreshold>10000</backPressureObjectThreshold>
            <destination>
                <groupId>c1783d42-645f-3380-0000-000000000000</groupId>
                <id>407c5cd1-0a0c-3634-0000-000000000000</id>
                <type>FUNNEL</type>
            </destination>
            <flowFileExpiration>0 sec</flowFileExpiration>
            <labelIndex>1</labelIndex>
            <loadBalanceCompression>DO_NOT_COMPRESS</loadBalanceCompression>
            <loadBalancePartitionAttribute></loadBalancePartitionAttribute>
            <loadBalanceStatus>LOAD_BALANCE_NOT_CONFIGURED</loadBalanceStatus>
            <loadBalanceStrategy>DO_NOT_LOAD_BALANCE</loadBalanceStrategy>
            <name></name>
            <selectedRelationships>failure</selectedRelationships>
            <source>
                <groupId>c1783d42-645f-3380-0000-000000000000</groupId>
                <id>e31e1369-1655-37e8-0000-000000000000</id>
                <type>PROCESSOR</type>
            </source>
            <zIndex>0</zIndex>
        </connections>
        <connections>
            <id>b47a3781-b8e5-34e5-0000-000000000000</id>
            <parentGroupId>c1783d42-645f-3380-0000-000000000000</parentGroupId>
            <backPressureDataSizeThreshold>100 MB</backPressureDataSizeThreshold>
            <backPressureObjectThreshold>10000</backPressureObjectThreshold>
            <bends>
                <x>16.404296875</x>
                <y>1504.6322683562378</y>
            </bends>
            <bends>
                <x>0.0</x>
                <y>1566.9356741179565</y>
            </bends>
            <destination>
                <groupId>c1783d42-645f-3380-0000-000000000000</groupId>
                <id>e31e1369-1655-37e8-0000-000000000000</id>
                <type>PROCESSOR</type>
            </destination>
            <flowFileExpiration>0 sec</flowFileExpiration>
            <labelIndex>1</labelIndex>
            <loadBalanceCompression>DO_NOT_COMPRESS</loadBalanceCompression>
            <loadBalancePartitionAttribute></loadBalancePartitionAttribute>
            <loadBalanceStatus>LOAD_BALANCE_NOT_CONFIGURED</loadBalanceStatus>
            <loadBalanceStrategy>DO_NOT_LOAD_BALANCE</loadBalanceStrategy>
            <name></name>
            <selectedRelationships>retry</selectedRelationships>
            <source>
                <groupId>c1783d42-645f-3380-0000-000000000000</groupId>
                <id>e31e1369-1655-37e8-0000-000000000000</id>
                <type>PROCESSOR</type>
            </source>
            <zIndex>0</zIndex>
        </connections>
        <connections>
            <id>bcf78509-8700-35e9-0000-000000000000</id>
            <parentGroupId>c1783d42-645f-3380-0000-000000000000</parentGroupId>
            <backPressureDataSizeThreshold>1 GB</backPressureDataSizeThreshold>
            <backPressureObjectThreshold>10000</backPressureObjectThreshold>
            <destination>
                <groupId>c1783d42-645f-3380-0000-000000000000</groupId>
                <id>fa42dc0a-369e-348c-0000-000000000000</id>
                <type>FUNNEL</type>
            </destination>
            <flowFileExpiration>0 sec</flowFileExpiration>
            <labelIndex>1</labelIndex>
            <loadBalanceCompression>DO_NOT_COMPRESS</loadBalanceCompression>
            <loadBalancePartitionAttribute></loadBalancePartitionAttribute>
            <loadBalanceStatus>LOAD_BALANCE_NOT_CONFIGURED</loadBalanceStatus>
            <loadBalanceStrategy>DO_NOT_LOAD_BALANCE</loadBalanceStrategy>
            <name></name>
            <selectedRelationships>failure</selectedRelationships>
            <source>
                <groupId>c1783d42-645f-3380-0000-000000000000</groupId>
                <id>4d1a2e16-aa25-38ed-0000-000000000000</id>
                <type>PROCESSOR</type>
            </source>
            <zIndex>0</zIndex>
        </connections>
        <connections>
            <id>cac1e1fc-1f68-3c91-0000-000000000000</id>
            <parentGroupId>c1783d42-645f-3380-0000-000000000000</parentGroupId>
            <backPressureDataSizeThreshold>100 MB</backPressureDataSizeThreshold>
            <backPressureObjectThreshold>10000</backPressureObjectThreshold>
            <bends>
                <x>1271.2222632887197</x>
                <y>1535.7715081771787</y>
            </bends>
            <bends>
                <x>1271.2222632887197</x>
                <y>1585.7715081771787</y>
            </bends>
            <destination>
                <groupId>c1783d42-645f-3380-0000-000000000000</groupId>
                <id>9ca0eb06-eb43-3e1a-0000-000000000000</id>
                <type>PROCESSOR</type>
            </destination>
            <flowFileExpiration>0 sec</flowFileExpiration>
            <labelIndex>1</labelIndex>
            <loadBalanceCompression>DO_NOT_COMPRESS</loadBalanceCompression>
            <loadBalancePartitionAttribute></loadBalancePartitionAttribute>
            <loadBalanceStatus>LOAD_BALANCE_NOT_CONFIGURED</loadBalanceStatus>
            <loadBalanceStrategy>DO_NOT_LOAD_BALANCE</loadBalanceStrategy>
            <name></name>
            <selectedRelationships>retry</selectedRelationships>
            <source>
                <groupId>c1783d42-645f-3380-0000-000000000000</groupId>
                <id>9ca0eb06-eb43-3e1a-0000-000000000000</id>
                <type>PROCESSOR</type>
            </source>
            <zIndex>0</zIndex>
        </connections>
        <connections>
            <id>f341efc3-8a7f-35ba-0000-000000000000</id>
            <parentGroupId>c1783d42-645f-3380-0000-000000000000</parentGroupId>
            <backPressureDataSizeThreshold>1 GB</backPressureDataSizeThreshold>
            <backPressureObjectThreshold>10000</backPressureObjectThreshold>
            <bends>
                <x>939.7549885605858</x>
                <y>742.0265413234779</y>
            </bends>
            <bends>
                <x>939.7549885605858</x>
                <y>792.0265413234779</y>
            </bends>
            <destination>
                <groupId>c1783d42-645f-3380-0000-000000000000</groupId>
                <id>89eef85f-3cfa-303b-0000-000000000000</id>
                <type>PROCESSOR</type>
            </destination>
            <flowFileExpiration>0 sec</flowFileExpiration>
            <labelIndex>1</labelIndex>
            <loadBalanceCompression>DO_NOT_COMPRESS</loadBalanceCompression>
            <loadBalancePartitionAttribute></loadBalancePartitionAttribute>
            <loadBalanceStatus>LOAD_BALANCE_NOT_CONFIGURED</loadBalanceStatus>
            <loadBalanceStrategy>DO_NOT_LOAD_BALANCE</loadBalanceStrategy>
            <name></name>
            <selectedRelationships>Retry</selectedRelationships>
            <source>
                <groupId>c1783d42-645f-3380-0000-000000000000</groupId>
                <id>89eef85f-3cfa-303b-0000-000000000000</id>
                <type>PROCESSOR</type>
            </source>
            <zIndex>0</zIndex>
        </connections>
        <connections>
            <id>f70c770d-ac3a-3e16-0000-000000000000</id>
            <parentGroupId>c1783d42-645f-3380-0000-000000000000</parentGroupId>
            <backPressureDataSizeThreshold>100 MB</backPressureDataSizeThreshold>
            <backPressureObjectThreshold>10000</backPressureObjectThreshold>
            <destination>
                <groupId>c1783d42-645f-3380-0000-000000000000</groupId>
                <id>614be727-96a2-32b4-0000-000000000000</id>
                <type>PROCESSOR</type>
            </destination>
            <flowFileExpiration>0 sec</flowFileExpiration>
            <labelIndex>1</labelIndex>
            <loadBalanceCompression>DO_NOT_COMPRESS</loadBalanceCompression>
            <loadBalancePartitionAttribute></loadBalancePartitionAttribute>
            <loadBalanceStatus>LOAD_BALANCE_NOT_CONFIGURED</loadBalanceStatus>
            <loadBalanceStrategy>DO_NOT_LOAD_BALANCE</loadBalanceStrategy>
            <name></name>
            <selectedRelationships>success</selectedRelationships>
            <source>
                <groupId>c1783d42-645f-3380-0000-000000000000</groupId>
                <id>005c59d5-16b8-375e-0000-000000000000</id>
                <type>PROCESSOR</type>
            </source>
            <zIndex>0</zIndex>
        </connections>
        <connections>
            <id>fd1c4d6e-4737-36ce-0000-000000000000</id>
            <parentGroupId>c1783d42-645f-3380-0000-000000000000</parentGroupId>
            <backPressureDataSizeThreshold>100 MB</backPressureDataSizeThreshold>
            <backPressureObjectThreshold>10000</backPressureObjectThreshold>
            <destination>
                <groupId>c1783d42-645f-3380-0000-000000000000</groupId>
                <id>5ce096b6-e3f8-32f0-0000-000000000000</id>
                <type>FUNNEL</type>
            </destination>
            <flowFileExpiration>0 sec</flowFileExpiration>
            <labelIndex>1</labelIndex>
            <loadBalanceCompression>DO_NOT_COMPRESS</loadBalanceCompression>
            <loadBalancePartitionAttribute></loadBalancePartitionAttribute>
            <loadBalanceStatus>LOAD_BALANCE_NOT_CONFIGURED</loadBalanceStatus>
            <loadBalanceStrategy>DO_NOT_LOAD_BALANCE</loadBalanceStrategy>
            <name></name>
            <selectedRelationships>failure</selectedRelationships>
            <source>
                <groupId>c1783d42-645f-3380-0000-000000000000</groupId>
                <id>614be727-96a2-32b4-0000-000000000000</id>
                <type>PROCESSOR</type>
            </source>
            <zIndex>0</zIndex>
        </connections>
        <controllerServices>
            <id>25fd775d-f0f5-3661-0000-000000000000</id>
            <parentGroupId>c1783d42-645f-3380-0000-000000000000</parentGroupId>
            <bundle>
                <artifact>nifi-record-serialization-services-nar</artifact>
                <group>org.apache.nifi</group>
                <version>1.9.2</version>
            </bundle>
            <comments></comments>
            <descriptors>
                <entry>
                    <key>schema-access-strategy</key>
                    <value>
                        <name>schema-access-strategy</name>
                    </value>
                </entry>
                <entry>
                    <key>schema-registry</key>
                    <value>
                        <identifiesControllerService>org.apache.nifi.schemaregistry.services.SchemaRegistry</identifiesControllerService>
                        <name>schema-registry</name>
                    </value>
                </entry>
                <entry>
                    <key>schema-name</key>
                    <value>
                        <name>schema-name</name>
                    </value>
                </entry>
                <entry>
                    <key>schema-version</key>
                    <value>
                        <name>schema-version</name>
                    </value>
                </entry>
                <entry>
                    <key>schema-branch</key>
                    <value>
                        <name>schema-branch</name>
                    </value>
                </entry>
                <entry>
                    <key>schema-text</key>
                    <value>
                        <name>schema-text</name>
                    </value>
                </entry>
                <entry>
                    <key>cache-size</key>
                    <value>
                        <name>cache-size</name>
                    </value>
                </entry>
            </descriptors>
            <name>AvroReader</name>
            <persistsState>false</persistsState>
            <properties>
                <entry>
                    <key>schema-access-strategy</key>
                    <value>embedded-avro-schema</value>
                </entry>
                <entry>
                    <key>schema-registry</key>
                </entry>
                <entry>
                    <key>schema-name</key>
                    <value>${schema.name}</value>
                </entry>
                <entry>
                    <key>schema-version</key>
                </entry>
                <entry>
                    <key>schema-branch</key>
                </entry>
                <entry>
                    <key>schema-text</key>
                    <value>${avro.schema}</value>
                </entry>
                <entry>
                    <key>cache-size</key>
                    <value>1000</value>
                </entry>
            </properties>
            <state>ENABLED</state>
            <type>org.apache.nifi.avro.AvroReader</type>
        </controllerServices>
        <controllerServices>
            <id>2dd05315-3ae2-38a1-0000-000000000000</id>
            <parentGroupId>c1783d42-645f-3380-0000-000000000000</parentGroupId>
            <bundle>
                <artifact>nifi-dbcp-service-nar</artifact>
                <group>org.apache.nifi</group>
                <version>1.9.2</version>
            </bundle>
            <comments></comments>
            <descriptors>
                <entry>
                    <key>Database Connection URL</key>
                    <value>
                        <name>Database Connection URL</name>
                    </value>
                </entry>
                <entry>
                    <key>Database Driver Class Name</key>
                    <value>
                        <name>Database Driver Class Name</name>
                    </value>
                </entry>
                <entry>
                    <key>database-driver-locations</key>
                    <value>
                        <name>database-driver-locations</name>
                    </value>
                </entry>
                <entry>
                    <key>kerberos-credentials-service</key>
                    <value>
                        <identifiesControllerService>org.apache.nifi.kerberos.KerberosCredentialsService</identifiesControllerService>
                        <name>kerberos-credentials-service</name>
                    </value>
                </entry>
                <entry>
                    <key>Database User</key>
                    <value>
                        <name>Database User</name>
                    </value>
                </entry>
                <entry>
                    <key>Password</key>
                    <value>
                        <name>Password</name>
                    </value>
                </entry>
                <entry>
                    <key>Max Wait Time</key>
                    <value>
                        <name>Max Wait Time</name>
                    </value>
                </entry>
                <entry>
                    <key>Max Total Connections</key>
                    <value>
                        <name>Max Total Connections</name>
                    </value>
                </entry>
                <entry>
                    <key>Validation-query</key>
                    <value>
                        <name>Validation-query</name>
                    </value>
                </entry>
                <entry>
                    <key>dbcp-min-idle-conns</key>
                    <value>
                        <name>dbcp-min-idle-conns</name>
                    </value>
                </entry>
                <entry>
                    <key>dbcp-max-idle-conns</key>
                    <value>
                        <name>dbcp-max-idle-conns</name>
                    </value>
                </entry>
                <entry>
                    <key>dbcp-max-conn-lifetime</key>
                    <value>
                        <name>dbcp-max-conn-lifetime</name>
                    </value>
                </entry>
                <entry>
                    <key>dbcp-time-between-eviction-runs</key>
                    <value>
                        <name>dbcp-time-between-eviction-runs</name>
                    </value>
                </entry>
                <entry>
                    <key>dbcp-min-evictable-idle-time</key>
                    <value>
                        <name>dbcp-min-evictable-idle-time</name>
                    </value>
                </entry>
                <entry>
                    <key>dbcp-soft-min-evictable-idle-time</key>
                    <value>
                        <name>dbcp-soft-min-evictable-idle-time</name>
                    </value>
                </entry>
            </descriptors>
            <name>DBCPConnectionPool-MTSamples</name>
            <persistsState>false</persistsState>
            <properties>
                <entry>
                    <key>Database Connection URL</key>
                    <value>jdbc:postgresql://samples-db:5432/db_samples</value>
                </entry>
                <entry>
                    <key>Database Driver Class Name</key>
                    <value>org.postgresql.Driver</value>
                </entry>
                <entry>
                    <key>database-driver-locations</key>
                    <value>/opt/nifi/drivers/postgresql-42.2.5.jar</value>
                </entry>
                <entry>
                    <key>kerberos-credentials-service</key>
                </entry>
                <entry>
                    <key>Database User</key>
                    <value>test</value>
                </entry>
                <entry>
                    <key>Password</key>
                </entry>
                <entry>
                    <key>Max Wait Time</key>
                    <value>500 millis</value>
                </entry>
                <entry>
                    <key>Max Total Connections</key>
                    <value>8</value>
                </entry>
                <entry>
                    <key>Validation-query</key>
                </entry>
                <entry>
                    <key>dbcp-min-idle-conns</key>
                    <value>0</value>
                </entry>
                <entry>
                    <key>dbcp-max-idle-conns</key>
                    <value>8</value>
                </entry>
                <entry>
                    <key>dbcp-max-conn-lifetime</key>
                    <value>-1</value>
                </entry>
                <entry>
                    <key>dbcp-time-between-eviction-runs</key>
                    <value>-1</value>
                </entry>
                <entry>
                    <key>dbcp-min-evictable-idle-time</key>
                    <value>30 mins</value>
                </entry>
                <entry>
                    <key>dbcp-soft-min-evictable-idle-time</key>
                    <value>-1</value>
                </entry>
            </properties>
            <state>ENABLED</state>
            <type>org.apache.nifi.dbcp.DBCPConnectionPool</type>
        </controllerServices>
        <controllerServices>
            <id>50ecd5b3-11cd-3229-0000-000000000000</id>
            <parentGroupId>c1783d42-645f-3380-0000-000000000000</parentGroupId>
            <bundle>
                <artifact>nifi-dbcp-service-nar</artifact>
                <group>org.apache.nifi</group>
                <version>1.9.2</version>
            </bundle>
            <comments></comments>
            <descriptors>
                <entry>
                    <key>Database Connection URL</key>
                    <value>
                        <name>Database Connection URL</name>
                    </value>
                </entry>
                <entry>
                    <key>Database Driver Class Name</key>
                    <value>
                        <name>Database Driver Class Name</name>
                    </value>
                </entry>
                <entry>
                    <key>database-driver-locations</key>
                    <value>
                        <name>database-driver-locations</name>
                    </value>
                </entry>
                <entry>
                    <key>kerberos-credentials-service</key>
                    <value>
                        <identifiesControllerService>org.apache.nifi.kerberos.KerberosCredentialsService</identifiesControllerService>
                        <name>kerberos-credentials-service</name>
                    </value>
                </entry>
                <entry>
                    <key>Database User</key>
                    <value>
                        <name>Database User</name>
                    </value>
                </entry>
                <entry>
                    <key>Password</key>
                    <value>
                        <name>Password</name>
                    </value>
                </entry>
                <entry>
                    <key>Max Wait Time</key>
                    <value>
                        <name>Max Wait Time</name>
                    </value>
                </entry>
                <entry>
                    <key>Max Total Connections</key>
                    <value>
                        <name>Max Total Connections</name>
                    </value>
                </entry>
                <entry>
                    <key>Validation-query</key>
                    <value>
                        <name>Validation-query</name>
                    </value>
                </entry>
                <entry>
                    <key>dbcp-min-idle-conns</key>
                    <value>
                        <name>dbcp-min-idle-conns</name>
                    </value>
                </entry>
                <entry>
                    <key>dbcp-max-idle-conns</key>
                    <value>
                        <name>dbcp-max-idle-conns</name>
                    </value>
                </entry>
                <entry>
                    <key>dbcp-max-conn-lifetime</key>
                    <value>
                        <name>dbcp-max-conn-lifetime</name>
                    </value>
                </entry>
                <entry>
                    <key>dbcp-time-between-eviction-runs</key>
                    <value>
                        <name>dbcp-time-between-eviction-runs</name>
                    </value>
                </entry>
                <entry>
                    <key>dbcp-min-evictable-idle-time</key>
                    <value>
                        <name>dbcp-min-evictable-idle-time</name>
                    </value>
                </entry>
                <entry>
                    <key>dbcp-soft-min-evictable-idle-time</key>
                    <value>
                        <name>dbcp-soft-min-evictable-idle-time</name>
                    </value>
                </entry>
            </descriptors>
            <name>DBCPConnectionPool-MTSamples-write</name>
            <persistsState>false</persistsState>
            <properties>
                <entry>
                    <key>Database Connection URL</key>
                    <value>jdbc:postgresql://samples-db:5432/db_samples?stringtype=unspecified</value>
                </entry>
                <entry>
                    <key>Database Driver Class Name</key>
                    <value>org.postgresql.Driver</value>
                </entry>
                <entry>
                    <key>database-driver-locations</key>
                    <value>/opt/nifi/drivers/postgresql-42.2.5.jar</value>
                </entry>
                <entry>
                    <key>kerberos-credentials-service</key>
                </entry>
                <entry>
                    <key>Database User</key>
                    <value>test</value>
                </entry>
                <entry>
                    <key>Password</key>
                </entry>
                <entry>
                    <key>Max Wait Time</key>
                    <value>500 millis</value>
                </entry>
                <entry>
                    <key>Max Total Connections</key>
                    <value>8</value>
                </entry>
                <entry>
                    <key>Validation-query</key>
                </entry>
                <entry>
                    <key>dbcp-min-idle-conns</key>
                    <value>0</value>
                </entry>
                <entry>
                    <key>dbcp-max-idle-conns</key>
                    <value>8</value>
                </entry>
                <entry>
                    <key>dbcp-max-conn-lifetime</key>
                    <value>-1</value>
                </entry>
                <entry>
                    <key>dbcp-time-between-eviction-runs</key>
                    <value>-1</value>
                </entry>
                <entry>
                    <key>dbcp-min-evictable-idle-time</key>
                    <value>30 mins</value>
                </entry>
                <entry>
                    <key>dbcp-soft-min-evictable-idle-time</key>
                    <value>-1</value>
                </entry>
            </properties>
            <state>ENABLED</state>
            <type>org.apache.nifi.dbcp.DBCPConnectionPool</type>
        </controllerServices>
        <funnels>
            <id>407c5cd1-0a0c-3634-0000-000000000000</id>
            <parentGroupId>c1783d42-645f-3380-0000-000000000000</parentGroupId>
            <position>
                <x>647.7356539573861</x>
                <y>1749.285583682783</y>
            </position>
        </funnels>
        <funnels>
            <id>5ce096b6-e3f8-32f0-0000-000000000000</id>
            <parentGroupId>c1783d42-645f-3380-0000-000000000000</parentGroupId>
            <position>
                <x>118.55644840731384</x>
                <y>1212.9837133727722</y>
            </position>
        </funnels>
        <funnels>
            <id>fa42dc0a-369e-348c-0000-000000000000</id>
            <parentGroupId>c1783d42-645f-3380-0000-000000000000</parentGroupId>
            <position>
                <x>135.7738251162982</x>
                <y>732.0968801818542</y>
            </position>
        </funnels>
        <processors>
            <id>005c59d5-16b8-375e-0000-000000000000</id>
            <parentGroupId>c1783d42-645f-3380-0000-000000000000</parentGroupId>
            <position>
                <x>481.0919481559031</x>
                <y>943.5620860936976</y>
            </position>
            <bundle>
                <artifact>nifi-scripting-nar</artifact>
                <group>org.apache.nifi</group>
                <version>1.9.2</version>
            </bundle>
            <config>
                <bulletinLevel>WARN</bulletinLevel>
                <comments></comments>
                <concurrentlySchedulableTaskCount>2</concurrentlySchedulableTaskCount>
                <descriptors>
                    <entry>
                        <key>Script Engine</key>
                        <value>
                            <name>Script Engine</name>
                        </value>
                    </entry>
                    <entry>
                        <key>Script File</key>
                        <value>
                            <name>Script File</name>
                        </value>
                    </entry>
                    <entry>
                        <key>Script Body</key>
                        <value>
                            <name>Script Body</name>
                        </value>
                    </entry>
                    <entry>
                        <key>Module Directory</key>
                        <value>
                            <name>Module Directory</name>
                        </value>
                    </entry>
                </descriptors>
                <executionNode>ALL</executionNode>
                <lossTolerant>false</lossTolerant>
                <penaltyDuration>30 sec</penaltyDuration>
                <properties>
                    <entry>
                        <key>Script Engine</key>
                        <value>Groovy</value>
                    </entry>
                    <entry>
                        <key>Script File</key>
                        <value>/devel/user-scripts/parse-tika-response-single.groovy</value>
                    </entry>
                    <entry>
                        <key>Script Body</key>
                    </entry>
                    <entry>
                        <key>Module Directory</key>
                    </entry>
                </properties>
                <runDurationMillis>0</runDurationMillis>
                <schedulingPeriod>0 sec</schedulingPeriod>
                <schedulingStrategy>TIMER_DRIVEN</schedulingStrategy>
                <yieldDuration>1 sec</yieldDuration>
            </config>
            <executionNodeRestricted>false</executionNodeRestricted>
            <name>ExecuteScript-ParseTikaResponse</name>
            <relationships>
                <autoTerminate>false</autoTerminate>
                <name>failure</name>
            </relationships>
            <relationships>
                <autoTerminate>false</autoTerminate>
                <name>success</name>
            </relationships>
            <state>STOPPED</state>
            <style/>
            <type>org.apache.nifi.processors.script.ExecuteScript</type>
        </processors>
        <processors>
            <id>4d1a2e16-aa25-38ed-0000-000000000000</id>
            <parentGroupId>c1783d42-645f-3380-0000-000000000000</parentGroupId>
            <position>
                <x>469.0333772940867</x>
                <y>451.23274039057264</y>
            </position>
            <bundle>
                <artifact>nifi-scripting-nar</artifact>
                <group>org.apache.nifi</group>
                <version>1.9.2</version>
            </bundle>
            <config>
                <bulletinLevel>WARN</bulletinLevel>
                <comments></comments>
                <concurrentlySchedulableTaskCount>1</concurrentlySchedulableTaskCount>
                <descriptors>
                    <entry>
                        <key>Script Engine</key>
                        <value>
                            <name>Script Engine</name>
                        </value>
                    </entry>
                    <entry>
                        <key>Script File</key>
                        <value>
                            <name>Script File</name>
                        </value>
                    </entry>
                    <entry>
                        <key>Script Body</key>
                        <value>
                            <name>Script Body</name>
                        </value>
                    </entry>
                    <entry>
                        <key>Module Directory</key>
                        <value>
                            <name>Module Directory</name>
                        </value>
                    </entry>
                    <entry>
                        <key>binary_field</key>
                        <value>
                            <name>binary_field</name>
                        </value>
                    </entry>
                    <entry>
                        <key>document_id_field</key>
                        <value>
                            <name>document_id_field</name>
                        </value>
                    </entry>
                </descriptors>
                <executionNode>ALL</executionNode>
                <lossTolerant>false</lossTolerant>
                <penaltyDuration>30 sec</penaltyDuration>
                <properties>
                    <entry>
                        <key>Script Engine</key>
                        <value>Groovy</value>
                    </entry>
                    <entry>
                        <key>Script File</key>
                        <value>/devel/user-scripts/prepare-db-record-for-tika-request-single.groovy</value>
                    </entry>
                    <entry>
                        <key>Script Body</key>
                    </entry>
                    <entry>
                        <key>Module Directory</key>
                    </entry>
                    <entry>
                        <key>binary_field</key>
                        <value>binarydoc</value>
                    </entry>
                    <entry>
                        <key>document_id_field</key>
                        <value>docid</value>
                    </entry>
                </properties>
                <runDurationMillis>0</runDurationMillis>
                <schedulingPeriod>0 sec</schedulingPeriod>
                <schedulingStrategy>TIMER_DRIVEN</schedulingStrategy>
                <yieldDuration>1 sec</yieldDuration>
            </config>
            <executionNodeRestricted>false</executionNodeRestricted>
            <name>ExecuteScript-PrepareTikaContent</name>
            <relationships>
                <autoTerminate>false</autoTerminate>
                <name>failure</name>
            </relationships>
            <relationships>
                <autoTerminate>false</autoTerminate>
                <name>success</name>
            </relationships>
            <state>STOPPED</state>
            <style/>
            <type>org.apache.nifi.processors.script.ExecuteScript</type>
        </processors>
        <processors>
            <id>614be727-96a2-32b4-0000-000000000000</id>
            <parentGroupId>c1783d42-645f-3380-0000-000000000000</parentGroupId>
            <position>
                <x>477.0649282638128</x>
                <y>1212.9791440550794</y>
            </position>
            <bundle>
                <artifact>nifi-groovyx-nar</artifact>
                <group>org.apache.nifi</group>
                <version>1.9.2</version>
            </bundle>
            <config>
                <bulletinLevel>WARN</bulletinLevel>
                <comments></comments>
                <concurrentlySchedulableTaskCount>1</concurrentlySchedulableTaskCount>
                <descriptors>
                    <entry>
                        <key>groovyx-script-file</key>
                        <value>
                            <name>groovyx-script-file</name>
                        </value>
                    </entry>
                    <entry>
                        <key>groovyx-script-body</key>
                        <value>
                            <name>groovyx-script-body</name>
                        </value>
                    </entry>
                    <entry>
                        <key>groovyx-failure-strategy</key>
                        <value>
                            <name>groovyx-failure-strategy</name>
                        </value>
                    </entry>
                    <entry>
                        <key>groovyx-additional-classpath</key>
                        <value>
                            <name>groovyx-additional-classpath</name>
                        </value>
                    </entry>
                    <entry>
                        <key>avro_schema_path</key>
                        <value>
                            <name>avro_schema_path</name>
                        </value>
                    </entry>
                </descriptors>
                <executionNode>ALL</executionNode>
                <lossTolerant>false</lossTolerant>
                <penaltyDuration>30 sec</penaltyDuration>
                <properties>
                    <entry>
                        <key>groovyx-script-file</key>
                        <value>/devel/user-scripts/parse-tika-result-json-to-avro.groovy</value>
                    </entry>
                    <entry>
                        <key>groovyx-script-body</key>
                    </entry>
                    <entry>
                        <key>groovyx-failure-strategy</key>
                        <value>rollback</value>
                    </entry>
                    <entry>
                        <key>groovyx-additional-classpath</key>
                    </entry>
                    <entry>
                        <key>avro_schema_path</key>
                        <value>/devel/user-scripts/schemas/document.avsc</value>
                    </entry>
                </properties>
                <runDurationMillis>0</runDurationMillis>
                <schedulingPeriod>0 sec</schedulingPeriod>
                <schedulingStrategy>TIMER_DRIVEN</schedulingStrategy>
                <yieldDuration>1 sec</yieldDuration>
            </config>
            <executionNodeRestricted>false</executionNodeRestricted>
            <name>ExecuteGroovyScript-ConvertJsonToAvro</name>
            <relationships>
                <autoTerminate>false</autoTerminate>
                <name>failure</name>
            </relationships>
            <relationships>
                <autoTerminate>false</autoTerminate>
                <name>success</name>
            </relationships>
            <state>STOPPED</state>
            <style/>
            <type>org.apache.nifi.processors.groovyx.ExecuteGroovyScript</type>
        </processors>
        <processors>
            <id>89eef85f-3cfa-303b-0000-000000000000</id>
            <parentGroupId>c1783d42-645f-3380-0000-000000000000</parentGroupId>
            <position>
                <x>476.75498856058584</x>
                <y>702.0265413234779</y>
            </position>
            <bundle>
                <artifact>nifi-standard-nar</artifact>
                <group>org.apache.nifi</group>
                <version>1.9.2</version>
            </bundle>
            <config>
                <bulletinLevel>WARN</bulletinLevel>
                <comments></comments>
                <concurrentlySchedulableTaskCount>1</concurrentlySchedulableTaskCount>
                <descriptors>
                    <entry>
                        <key>HTTP Method</key>
                        <value>
                            <name>HTTP Method</name>
                        </value>
                    </entry>
                    <entry>
                        <key>Remote URL</key>
                        <value>
                            <name>Remote URL</name>
                        </value>
                    </entry>
                    <entry>
                        <key>SSL Context Service</key>
                        <value>
                            <identifiesControllerService>org.apache.nifi.ssl.SSLContextService</identifiesControllerService>
                            <name>SSL Context Service</name>
                        </value>
                    </entry>
                    <entry>
                        <key>Connection Timeout</key>
                        <value>
                            <name>Connection Timeout</name>
                        </value>
                    </entry>
                    <entry>
                        <key>Read Timeout</key>
                        <value>
                            <name>Read Timeout</name>
                        </value>
                    </entry>
                    <entry>
                        <key>Include Date Header</key>
                        <value>
                            <name>Include Date Header</name>
                        </value>
                    </entry>
                    <entry>
                        <key>Follow Redirects</key>
                        <value>
                            <name>Follow Redirects</name>
                        </value>
                    </entry>
                    <entry>
                        <key>Attributes to Send</key>
                        <value>
                            <name>Attributes to Send</name>
                        </value>
                    </entry>
                    <entry>
                        <key>Basic Authentication Username</key>
                        <value>
                            <name>Basic Authentication Username</name>
                        </value>
                    </entry>
                    <entry>
                        <key>Basic Authentication Password</key>
                        <value>
                            <name>Basic Authentication Password</name>
                        </value>
                    </entry>
                    <entry>
                        <key>proxy-configuration-service</key>
                        <value>
                            <identifiesControllerService>org.apache.nifi.proxy.ProxyConfigurationService</identifiesControllerService>
                            <name>proxy-configuration-service</name>
                        </value>
                    </entry>
                    <entry>
                        <key>Proxy Host</key>
                        <value>
                            <name>Proxy Host</name>
                        </value>
                    </entry>
                    <entry>
                        <key>Proxy Port</key>
                        <value>
                            <name>Proxy Port</name>
                        </value>
                    </entry>
                    <entry>
                        <key>Proxy Type</key>
                        <value>
                            <name>Proxy Type</name>
                        </value>
                    </entry>
                    <entry>
                        <key>invokehttp-proxy-user</key>
                        <value>
                            <name>invokehttp-proxy-user</name>
                        </value>
                    </entry>
                    <entry>
                        <key>invokehttp-proxy-password</key>
                        <value>
                            <name>invokehttp-proxy-password</name>
                        </value>
                    </entry>
                    <entry>
                        <key>Put Response Body In Attribute</key>
                        <value>
                            <name>Put Response Body In Attribute</name>
                        </value>
                    </entry>
                    <entry>
                        <key>Max Length To Put In Attribute</key>
                        <value>
                            <name>Max Length To Put In Attribute</name>
                        </value>
                    </entry>
                    <entry>
                        <key>Digest Authentication</key>
                        <value>
                            <name>Digest Authentication</name>
                        </value>
                    </entry>
                    <entry>
                        <key>Always Output Response</key>
                        <value>
                            <name>Always Output Response</name>
                        </value>
                    </entry>
                    <entry>
                        <key>Trusted Hostname</key>
                        <value>
                            <name>Trusted Hostname</name>
                        </value>
                    </entry>
                    <entry>
                        <key>Add Response Headers to Request</key>
                        <value>
                            <name>Add Response Headers to Request</name>
                        </value>
                    </entry>
                    <entry>
                        <key>Content-Type</key>
                        <value>
                            <name>Content-Type</name>
                        </value>
                    </entry>
                    <entry>
                        <key>send-message-body</key>
                        <value>
                            <name>send-message-body</name>
                        </value>
                    </entry>
                    <entry>
                        <key>Use Chunked Encoding</key>
                        <value>
                            <name>Use Chunked Encoding</name>
                        </value>
                    </entry>
                    <entry>
                        <key>Penalize on "No Retry"</key>
                        <value>
                            <name>Penalize on "No Retry"</name>
                        </value>
                    </entry>
                    <entry>
                        <key>use-etag</key>
                        <value>
                            <name>use-etag</name>
                        </value>
                    </entry>
                    <entry>
                        <key>etag-max-cache-size</key>
                        <value>
                            <name>etag-max-cache-size</name>
                        </value>
                    </entry>
                </descriptors>
                <executionNode>ALL</executionNode>
                <lossTolerant>false</lossTolerant>
                <penaltyDuration>30 sec</penaltyDuration>
                <properties>
                    <entry>
                        <key>HTTP Method</key>
                        <value>POST</value>
                    </entry>
                    <entry>
                        <key>Remote URL</key>
                        <value>http://host.docker.internal:8090/api/process</value>
                    </entry>
                    <entry>
                        <key>SSL Context Service</key>
                    </entry>
                    <entry>
                        <key>Connection Timeout</key>
                        <value>5 secs</value>
                    </entry>
                    <entry>
                        <key>Read Timeout</key>
                        <value>600 secs</value>
                    </entry>
                    <entry>
                        <key>Include Date Header</key>
                        <value>True</value>
                    </entry>
                    <entry>
                        <key>Follow Redirects</key>
                        <value>False</value>
                    </entry>
                    <entry>
                        <key>Attributes to Send</key>
                    </entry>
                    <entry>
                        <key>Basic Authentication Username</key>
                    </entry>
                    <entry>
                        <key>Basic Authentication Password</key>
                    </entry>
                    <entry>
                        <key>proxy-configuration-service</key>
                    </entry>
                    <entry>
                        <key>Proxy Host</key>
                    </entry>
                    <entry>
                        <key>Proxy Port</key>
                    </entry>
                    <entry>
                        <key>Proxy Type</key>
                        <value>http</value>
                    </entry>
                    <entry>
                        <key>invokehttp-proxy-user</key>
                    </entry>
                    <entry>
                        <key>invokehttp-proxy-password</key>
                    </entry>
                    <entry>
                        <key>Put Response Body In Attribute</key>
                    </entry>
                    <entry>
                        <key>Max Length To Put In Attribute</key>
                        <value>256</value>
                    </entry>
                    <entry>
                        <key>Digest Authentication</key>
                        <value>false</value>
                    </entry>
                    <entry>
                        <key>Always Output Response</key>
                        <value>false</value>
                    </entry>
                    <entry>
                        <key>Trusted Hostname</key>
                    </entry>
                    <entry>
                        <key>Add Response Headers to Request</key>
                        <value>false</value>
                    </entry>
                    <entry>
                        <key>Content-Type</key>
                        <value>${mime.type}</value>
                    </entry>
                    <entry>
                        <key>send-message-body</key>
                        <value>true</value>
                    </entry>
                    <entry>
                        <key>Use Chunked Encoding</key>
                        <value>false</value>
                    </entry>
                    <entry>
                        <key>Penalize on "No Retry"</key>
                        <value>false</value>
                    </entry>
                    <entry>
                        <key>use-etag</key>
                        <value>false</value>
                    </entry>
                    <entry>
                        <key>etag-max-cache-size</key>
                        <value>10MB</value>
                    </entry>
                </properties>
                <runDurationMillis>0</runDurationMillis>
                <schedulingPeriod>0 sec</schedulingPeriod>
                <schedulingStrategy>TIMER_DRIVEN</schedulingStrategy>
                <yieldDuration>1 sec</yieldDuration>
            </config>
            <executionNodeRestricted>false</executionNodeRestricted>
            <name>InvokeHTTP-QueryTika</name>
            <relationships>
                <autoTerminate>false</autoTerminate>
                <name>Failure</name>
            </relationships>
            <relationships>
                <autoTerminate>false</autoTerminate>
                <name>No Retry</name>
            </relationships>
            <relationships>
                <autoTerminate>true</autoTerminate>
                <name>Original</name>
            </relationships>
            <relationships>
                <autoTerminate>false</autoTerminate>
                <name>Response</name>
            </relationships>
            <relationships>
                <autoTerminate>false</autoTerminate>
                <name>Retry</name>
            </relationships>
            <state>STOPPED</state>
            <style/>
            <type>org.apache.nifi.processors.standard.InvokeHTTP</type>
        </processors>
        <processors>
            <id>9ca0eb06-eb43-3e1a-0000-000000000000</id>
            <parentGroupId>c1783d42-645f-3380-0000-000000000000</parentGroupId>
            <position>
                <x>808.2222632887197</x>
                <y>1495.7715081771787</y>
            </position>
            <bundle>
                <artifact>nifi-elasticsearch-nar</artifact>
                <group>org.apache.nifi</group>
                <version>1.9.2</version>
            </bundle>
            <config>
                <bulletinLevel>WARN</bulletinLevel>
                <comments></comments>
                <concurrentlySchedulableTaskCount>1</concurrentlySchedulableTaskCount>
                <descriptors>
                    <entry>
                        <key>elasticsearch-http-url</key>
                        <value>
                            <name>elasticsearch-http-url</name>
                        </value>
                    </entry>
                    <entry>
                        <key>SSL Context Service</key>
                        <value>
                            <identifiesControllerService>org.apache.nifi.ssl.SSLContextService</identifiesControllerService>
                            <name>SSL Context Service</name>
                        </value>
                    </entry>
                    <entry>
                        <key>Username</key>
                        <value>
                            <name>Username</name>
                        </value>
                    </entry>
                    <entry>
                        <key>Password</key>
                        <value>
                            <name>Password</name>
                        </value>
                    </entry>
                    <entry>
                        <key>elasticsearch-http-connect-timeout</key>
                        <value>
                            <name>elasticsearch-http-connect-timeout</name>
                        </value>
                    </entry>
                    <entry>
                        <key>elasticsearch-http-response-timeout</key>
                        <value>
                            <name>elasticsearch-http-response-timeout</name>
                        </value>
                    </entry>
                    <entry>
                        <key>proxy-configuration-service</key>
                        <value>
                            <identifiesControllerService>org.apache.nifi.proxy.ProxyConfigurationService</identifiesControllerService>
                            <name>proxy-configuration-service</name>
                        </value>
                    </entry>
                    <entry>
                        <key>elasticsearch-http-proxy-host</key>
                        <value>
                            <name>elasticsearch-http-proxy-host</name>
                        </value>
                    </entry>
                    <entry>
                        <key>elasticsearch-http-proxy-port</key>
                        <value>
                            <name>elasticsearch-http-proxy-port</name>
                        </value>
                    </entry>
                    <entry>
                        <key>proxy-username</key>
                        <value>
                            <name>proxy-username</name>
                        </value>
                    </entry>
                    <entry>
                        <key>proxy-password</key>
                        <value>
                            <name>proxy-password</name>
                        </value>
                    </entry>
                    <entry>
                        <key>put-es-record-record-reader</key>
                        <value>
                            <identifiesControllerService>org.apache.nifi.serialization.RecordReaderFactory</identifiesControllerService>
                            <name>put-es-record-record-reader</name>
                        </value>
                    </entry>
                    <entry>
                        <key>put-es-record-id-path</key>
                        <value>
                            <name>put-es-record-id-path</name>
                        </value>
                    </entry>
                    <entry>
                        <key>put-es-record-index</key>
                        <value>
                            <name>put-es-record-index</name>
                        </value>
                    </entry>
                    <entry>
                        <key>put-es-record-type</key>
                        <value>
                            <name>put-es-record-type</name>
                        </value>
                    </entry>
                    <entry>
                        <key>Character Set</key>
                        <value>
                            <name>Character Set</name>
                        </value>
                    </entry>
                    <entry>
                        <key>put-es-record-index-op</key>
                        <value>
                            <name>put-es-record-index-op</name>
                        </value>
                    </entry>
                    <entry>
                        <key>suppress-nulls</key>
                        <value>
                            <name>suppress-nulls</name>
                        </value>
                    </entry>
                    <entry>
                        <key>Date Format</key>
                        <value>
                            <name>Date Format</name>
                        </value>
                    </entry>
                    <entry>
                        <key>Time Format</key>
                        <value>
                            <name>Time Format</name>
                        </value>
                    </entry>
                    <entry>
                        <key>Timestamp Format</key>
                        <value>
                            <name>Timestamp Format</name>
                        </value>
                    </entry>
                </descriptors>
                <executionNode>ALL</executionNode>
                <lossTolerant>false</lossTolerant>
                <penaltyDuration>30 sec</penaltyDuration>
                <properties>
                    <entry>
                        <key>elasticsearch-http-url</key>
                        <value>http://elasticsearch-1:9200</value>
                    </entry>
                    <entry>
                        <key>SSL Context Service</key>
                    </entry>
                    <entry>
                        <key>Username</key>
                        <value>admin</value>
                    </entry>
                    <entry>
                        <key>Password</key>
                    </entry>
                    <entry>
                        <key>elasticsearch-http-connect-timeout</key>
                        <value>5 secs</value>
                    </entry>
                    <entry>
                        <key>elasticsearch-http-response-timeout</key>
                        <value>15 secs</value>
                    </entry>
                    <entry>
                        <key>proxy-configuration-service</key>
                    </entry>
                    <entry>
                        <key>elasticsearch-http-proxy-host</key>
                    </entry>
                    <entry>
                        <key>elasticsearch-http-proxy-port</key>
                    </entry>
                    <entry>
                        <key>proxy-username</key>
                    </entry>
                    <entry>
                        <key>proxy-password</key>
                    </entry>
                    <entry>
                        <key>put-es-record-record-reader</key>
                        <value>25fd775d-f0f5-3661-0000-000000000000</value>
                    </entry>
                    <entry>
                        <key>put-es-record-id-path</key>
                        <value>/doc_id</value>
                    </entry>
                    <entry>
                        <key>put-es-record-index</key>
                        <value>nifi_doc_tika_avro</value>
                    </entry>
                    <entry>
                        <key>put-es-record-type</key>
                        <value>_doc</value>
                    </entry>
                    <entry>
                        <key>Character Set</key>
                        <value>UTF-8</value>
                    </entry>
                    <entry>
                        <key>put-es-record-index-op</key>
                        <value>index</value>
                    </entry>
                    <entry>
                        <key>suppress-nulls</key>
                        <value>never-suppress</value>
                    </entry>
                    <entry>
                        <key>Date Format</key>
                    </entry>
                    <entry>
                        <key>Time Format</key>
                    </entry>
                    <entry>
                        <key>Timestamp Format</key>
                    </entry>
                </properties>
                <runDurationMillis>0</runDurationMillis>
                <schedulingPeriod>0 sec</schedulingPeriod>
                <schedulingStrategy>TIMER_DRIVEN</schedulingStrategy>
                <yieldDuration>1 sec</yieldDuration>
            </config>
            <executionNodeRestricted>false</executionNodeRestricted>
            <name>PutElasticsearchHttpRecord</name>
            <relationships>
                <autoTerminate>false</autoTerminate>
                <name>failure</name>
            </relationships>
            <relationships>
                <autoTerminate>false</autoTerminate>
                <name>retry</name>
            </relationships>
            <relationships>
                <autoTerminate>true</autoTerminate>
                <name>success</name>
            </relationships>
            <state>STOPPED</state>
            <style/>
            <type>org.apache.nifi.processors.elasticsearch.PutElasticsearchHttpRecord</type>
        </processors>
        <processors>
            <id>e31e1369-1655-37e8-0000-000000000000</id>
            <parentGroupId>c1783d42-645f-3380-0000-000000000000</parentGroupId>
            <position>
                <x>145.334228515625</x>
                <y>1470.1004385222534</y>
            </position>
            <bundle>
                <artifact>nifi-standard-nar</artifact>
                <group>org.apache.nifi</group>
                <version>1.9.2</version>
            </bundle>
            <config>
                <bulletinLevel>WARN</bulletinLevel>
                <comments></comments>
                <concurrentlySchedulableTaskCount>1</concurrentlySchedulableTaskCount>
                <descriptors>
                    <entry>
                        <key>put-db-record-record-reader</key>
                        <value>
                            <identifiesControllerService>org.apache.nifi.serialization.RecordReaderFactory</identifiesControllerService>
                            <name>put-db-record-record-reader</name>
                        </value>
                    </entry>
                    <entry>
                        <key>put-db-record-statement-type</key>
                        <value>
                            <name>put-db-record-statement-type</name>
                        </value>
                    </entry>
                    <entry>
                        <key>put-db-record-dcbp-service</key>
                        <value>
                            <identifiesControllerService>org.apache.nifi.dbcp.DBCPService</identifiesControllerService>
                            <name>put-db-record-dcbp-service</name>
                        </value>
                    </entry>
                    <entry>
                        <key>put-db-record-catalog-name</key>
                        <value>
                            <name>put-db-record-catalog-name</name>
                        </value>
                    </entry>
                    <entry>
                        <key>put-db-record-schema-name</key>
                        <value>
                            <name>put-db-record-schema-name</name>
                        </value>
                    </entry>
                    <entry>
                        <key>put-db-record-table-name</key>
                        <value>
                            <name>put-db-record-table-name</name>
                        </value>
                    </entry>
                    <entry>
                        <key>put-db-record-translate-field-names</key>
                        <value>
                            <name>put-db-record-translate-field-names</name>
                        </value>
                    </entry>
                    <entry>
                        <key>put-db-record-unmatched-field-behavior</key>
                        <value>
                            <name>put-db-record-unmatched-field-behavior</name>
                        </value>
                    </entry>
                    <entry>
                        <key>put-db-record-unmatched-column-behavior</key>
                        <value>
                            <name>put-db-record-unmatched-column-behavior</name>
                        </value>
                    </entry>
                    <entry>
                        <key>put-db-record-update-keys</key>
                        <value>
                            <name>put-db-record-update-keys</name>
                        </value>
                    </entry>
                    <entry>
                        <key>put-db-record-field-containing-sql</key>
                        <value>
                            <name>put-db-record-field-containing-sql</name>
                        </value>
                    </entry>
                    <entry>
                        <key>put-db-record-quoted-identifiers</key>
                        <value>
                            <name>put-db-record-quoted-identifiers</name>
                        </value>
                    </entry>
                    <entry>
                        <key>put-db-record-quoted-table-identifiers</key>
                        <value>
                            <name>put-db-record-quoted-table-identifiers</name>
                        </value>
                    </entry>
                    <entry>
                        <key>put-db-record-query-timeout</key>
                        <value>
                            <name>put-db-record-query-timeout</name>
                        </value>
                    </entry>
                    <entry>
                        <key>rollback-on-failure</key>
                        <value>
                            <name>rollback-on-failure</name>
                        </value>
                    </entry>
                    <entry>
                        <key>table-schema-cache-size</key>
                        <value>
                            <name>table-schema-cache-size</name>
                        </value>
                    </entry>
                    <entry>
                        <key>put-db-record-max-batch-size</key>
                        <value>
                            <name>put-db-record-max-batch-size</name>
                        </value>
                    </entry>
                </descriptors>
                <executionNode>ALL</executionNode>
                <lossTolerant>false</lossTolerant>
                <penaltyDuration>30 sec</penaltyDuration>
                <properties>
                    <entry>
                        <key>put-db-record-record-reader</key>
                        <value>25fd775d-f0f5-3661-0000-000000000000</value>
                    </entry>
                    <entry>
                        <key>put-db-record-statement-type</key>
                        <value>INSERT</value>
                    </entry>
                    <entry>
                        <key>put-db-record-dcbp-service</key>
                        <value>50ecd5b3-11cd-3229-0000-000000000000</value>
                    </entry>
                    <entry>
                        <key>put-db-record-catalog-name</key>
                    </entry>
                    <entry>
                        <key>put-db-record-schema-name</key>
                    </entry>
                    <entry>
                        <key>put-db-record-table-name</key>
                        <value>medical_reports_processed</value>
                    </entry>
                    <entry>
                        <key>put-db-record-translate-field-names</key>
                        <value>true</value>
                    </entry>
                    <entry>
                        <key>put-db-record-unmatched-field-behavior</key>
                        <value>Ignore Unmatched Fields</value>
                    </entry>
                    <entry>
                        <key>put-db-record-unmatched-column-behavior</key>
                        <value>Warn on Unmatched Columns</value>
                    </entry>
                    <entry>
                        <key>put-db-record-update-keys</key>
                    </entry>
                    <entry>
                        <key>put-db-record-field-containing-sql</key>
                    </entry>
                    <entry>
                        <key>put-db-record-quoted-identifiers</key>
                        <value>false</value>
                    </entry>
                    <entry>
                        <key>put-db-record-quoted-table-identifiers</key>
                        <value>false</value>
                    </entry>
                    <entry>
                        <key>put-db-record-query-timeout</key>
                        <value>0 seconds</value>
                    </entry>
                    <entry>
                        <key>rollback-on-failure</key>
                        <value>false</value>
                    </entry>
                    <entry>
                        <key>table-schema-cache-size</key>
                        <value>100</value>
                    </entry>
                    <entry>
                        <key>put-db-record-max-batch-size</key>
                        <value>0</value>
                    </entry>
                </properties>
                <runDurationMillis>0</runDurationMillis>
                <schedulingPeriod>0 sec</schedulingPeriod>
                <schedulingStrategy>TIMER_DRIVEN</schedulingStrategy>
                <yieldDuration>1 sec</yieldDuration>
            </config>
            <executionNodeRestricted>false</executionNodeRestricted>
            <name>PutDatabaseRecord</name>
            <relationships>
                <autoTerminate>false</autoTerminate>
                <name>failure</name>
            </relationships>
            <relationships>
                <autoTerminate>false</autoTerminate>
                <name>retry</name>
            </relationships>
            <relationships>
                <autoTerminate>true</autoTerminate>
                <name>success</name>
            </relationships>
            <state>STOPPED</state>
            <style/>
            <type>org.apache.nifi.processors.standard.PutDatabaseRecord</type>
        </processors>
        <processors>
            <id>f6dfc4f4-2311-371b-0000-000000000000</id>
            <parentGroupId>c1783d42-645f-3380-0000-000000000000</parentGroupId>
            <position>
                <x>465.67616856592485</x>
                <y>0.0</y>
            </position>
            <bundle>
                <artifact>nifi-standard-nar</artifact>
                <group>org.apache.nifi</group>
                <version>1.9.2</version>
            </bundle>
            <config>
                <bulletinLevel>WARN</bulletinLevel>
                <comments></comments>
                <concurrentlySchedulableTaskCount>1</concurrentlySchedulableTaskCount>
                <descriptors>
                    <entry>
                        <key>Database Connection Pooling Service</key>
                        <value>
                            <identifiesControllerService>org.apache.nifi.dbcp.DBCPService</identifiesControllerService>
                            <name>Database Connection Pooling Service</name>
                        </value>
                    </entry>
                    <entry>
                        <key>db-fetch-db-type</key>
                        <value>
                            <name>db-fetch-db-type</name>
                        </value>
                    </entry>
                    <entry>
                        <key>Table Name</key>
                        <value>
                            <name>Table Name</name>
                        </value>
                    </entry>
                    <entry>
                        <key>Columns to Return</key>
                        <value>
                            <name>Columns to Return</name>
                        </value>
                    </entry>
                    <entry>
                        <key>db-fetch-where-clause</key>
                        <value>
                            <name>db-fetch-where-clause</name>
                        </value>
                    </entry>
                    <entry>
                        <key>db-fetch-sql-query</key>
                        <value>
                            <name>db-fetch-sql-query</name>
                        </value>
                    </entry>
                    <entry>
                        <key>Maximum-value Columns</key>
                        <value>
                            <name>Maximum-value Columns</name>
                        </value>
                    </entry>
                    <entry>
                        <key>Max Wait Time</key>
                        <value>
                            <name>Max Wait Time</name>
                        </value>
                    </entry>
                    <entry>
                        <key>Fetch Size</key>
                        <value>
                            <name>Fetch Size</name>
                        </value>
                    </entry>
                    <entry>
                        <key>qdbt-max-rows</key>
                        <value>
                            <name>qdbt-max-rows</name>
                        </value>
                    </entry>
                    <entry>
                        <key>qdbt-output-batch-size</key>
                        <value>
                            <name>qdbt-output-batch-size</name>
                        </value>
                    </entry>
                    <entry>
                        <key>qdbt-max-frags</key>
                        <value>
                            <name>qdbt-max-frags</name>
                        </value>
                    </entry>
                    <entry>
                        <key>dbf-normalize</key>
                        <value>
                            <name>dbf-normalize</name>
                        </value>
                    </entry>
                    <entry>
                        <key>transaction-isolation-level</key>
                        <value>
                            <name>transaction-isolation-level</name>
                        </value>
                    </entry>
                    <entry>
                        <key>dbf-user-logical-types</key>
                        <value>
                            <name>dbf-user-logical-types</name>
                        </value>
                    </entry>
                    <entry>
                        <key>dbf-default-precision</key>
                        <value>
                            <name>dbf-default-precision</name>
                        </value>
                    </entry>
                    <entry>
                        <key>dbf-default-scale</key>
                        <value>
                            <name>dbf-default-scale</name>
                        </value>
                    </entry>
                </descriptors>
                <executionNode>PRIMARY</executionNode>
                <lossTolerant>false</lossTolerant>
                <penaltyDuration>30 sec</penaltyDuration>
                <properties>
                    <entry>
                        <key>Database Connection Pooling Service</key>
                        <value>2dd05315-3ae2-38a1-0000-000000000000</value>
                    </entry>
                    <entry>
                        <key>db-fetch-db-type</key>
                        <value>Generic</value>
                    </entry>
                    <entry>
                        <key>Table Name</key>
                        <value>medical_reports_raw</value>
                    </entry>
                    <entry>
                        <key>Columns to Return</key>
                        <value>docid, sampleid, dct, binarydoc</value>
                    </entry>
                    <entry>
                        <key>db-fetch-where-clause</key>
                    </entry>
                    <entry>
                        <key>db-fetch-sql-query</key>
                    </entry>
                    <entry>
                        <key>Maximum-value Columns</key>
                        <value>docid</value>
                    </entry>
                    <entry>
                        <key>Max Wait Time</key>
                        <value>0 seconds</value>
                    </entry>
                    <entry>
                        <key>Fetch Size</key>
                        <value>0</value>
                    </entry>
                    <entry>
                        <key>qdbt-max-rows</key>
                        <value>1</value>
                    </entry>
                    <entry>
                        <key>qdbt-output-batch-size</key>
                        <value>0</value>
                    </entry>
                    <entry>
                        <key>qdbt-max-frags</key>
                        <value>0</value>
                    </entry>
                    <entry>
                        <key>dbf-normalize</key>
                        <value>false</value>
                    </entry>
                    <entry>
                        <key>transaction-isolation-level</key>
                    </entry>
                    <entry>
                        <key>dbf-user-logical-types</key>
                        <value>false</value>
                    </entry>
                    <entry>
                        <key>dbf-default-precision</key>
                        <value>10</value>
                    </entry>
                    <entry>
                        <key>dbf-default-scale</key>
                        <value>0</value>
                    </entry>
                </properties>
                <runDurationMillis>0</runDurationMillis>
                <schedulingPeriod>0 sec</schedulingPeriod>
                <schedulingStrategy>TIMER_DRIVEN</schedulingStrategy>
                <yieldDuration>1 sec</yieldDuration>
            </config>
            <executionNodeRestricted>true</executionNodeRestricted>
            <name>QueryDatabaseTable</name>
            <relationships>
                <autoTerminate>false</autoTerminate>
                <name>success</name>
            </relationships>
            <state>STOPPED</state>
            <style/>
            <type>org.apache.nifi.processors.standard.QueryDatabaseTable</type>
        </processors>
    </snippet>
    <timestamp>12/09/2019 16:08:33 UTC</timestamp>
</template>
